anystrenum/__init__.py
anystrenum/anystrenum.py
anystrenum/inflected.py
AnyStrEnum-0.2.0.dist-info/LICENCE
AnyStrEnum-0.2.0.dist-info/METADATA
AnyStrEnum-0.2.0.dist-info/WHEEL
AnyStrEnum-0.2.0.dist-info/top_level.txt
AnyStrEnum-0.2.0.dist-info/RECORD
