Metadata-Version: 2.1
Name: AnyStrEnum
Version: 0.2.0
Summary: Elegant implementation of Enum which inherits from str or bytes
Home-page: UNKNOWN
Author: MrMrRobat
Author-email: appkiller16@gmail.com
License: MIT
Keywords: enum str strenum bytesenum bytestrenum typing auto autoenum
Platform: UNKNOWN
Classifier: Development Status :: 4 - Beta
Classifier: Intended Audience :: Developers
Classifier: Intended Audience :: System Administrators
Classifier: License :: OSI Approved :: MIT License
Classifier: Programming Language :: Python :: 3.7
Classifier: Topic :: Software Development :: Libraries :: Python Modules
Requires-Python: >=3.6
Provides-Extra: dev
Requires-Dist: pytest ; extra == 'dev'
Provides-Extra: inflection
Requires-Dist: inflection ; extra == 'inflection'
Provides-Extra: tests
Requires-Dist: pytest ; extra == 'tests'
